Mouritech_LoggingPerformance/LogPerformance.py
Mouritech_LoggingPerformance/__init__.py
Mouritech_LoggingPerformance/testPerformance.py
MT_PY_PerformanceLogging_Version1-0.0.1.dist-info/LICENSE.txt
MT_PY_PerformanceLogging_Version1-0.0.1.dist-info/METADATA
MT_PY_PerformanceLogging_Version1-0.0.1.dist-info/WHEEL
MT_PY_PerformanceLogging_Version1-0.0.1.dist-info/top_level.txt
MT_PY_PerformanceLogging_Version1-0.0.1.dist-info/RECORD
